eseg/__init__.py
eseg/config.py
eseg/stream.py
eseg/models/ConvLSTM.py
eseg/models/EventSurrealLayers.py
eseg/utils/dataviewers.py
eseg/utils/functions.py
eseg/utils/loaders.py
eseg-1.0.4.dist-info/licenses/LICENSE
eseg-1.0.4.dist-info/METADATA
eseg-1.0.4.dist-info/WHEEL
eseg-1.0.4.dist-info/top_level.txt
eseg-1.0.4.dist-info/RECORD
