Metadata-Version: 2.4
Name: eseg
Version: 1.0.4
Summary: Models and utilities for event-based depth / segmentation (Surreal benchmark).
Author-email: Martin Barry <martin.barry@gmail.com>
License: MIT License
Project-URL: Homepage, https://github.com/youruser/surreal-events
Project-URL: Repository, https://github.com/youruser/surreal-events
Project-URL: Issues, https://github.com/youruser/surreal-events/issues
Keywords: event-camera,computer-vision,deep-learning,pytorch,depth,surreal
Classifier: Development Status :: 3 - Alpha
Classifier: Intended Audience :: Science/Research
Classifier: License :: OSI Approved :: MIT License
Classifier: Programming Language :: Python :: 3
Classifier: Programming Language :: Python :: 3.10
Classifier: Programming Language :: Python :: 3.11
Classifier: Programming Language :: Python :: 3.12
Classifier: Topic :: Scientific/Engineering :: Artificial Intelligence
Requires-Python: ==3.12.*
License-File: LICENSE
Requires-Dist: opencv-python>=4.9.0
Requires-Dist: numpy<3.0,>=1.24
Requires-Dist: h5py>=3.10
Requires-Dist: tqdm>=4.64
Requires-Dist: lpips>=0.1.4
Requires-Dist: scikit-learn>=1.2
Requires-Dist: plotly>=5.18
Requires-Dist: pytorch-ignite>=0.5.2
Requires-Dist: matplotlib>=3.7
Requires-Dist: build>=1.3.0
Requires-Dist: twine>=6.1.0
Requires-Dist: bump>=1.3.2
Requires-Dist: dv-processing==2.0.2
Requires-Dist: imageio>=2.37.0
Provides-Extra: dev
Requires-Dist: black>=24.0; extra == "dev"
Requires-Dist: ruff>=0.4.0; extra == "dev"
Requires-Dist: mypy>=1.8.0; extra == "dev"
Requires-Dist: pytest>=8.0; extra == "dev"
Requires-Dist: pytest-cov>=4.1.0; extra == "dev"
Requires-Dist: types-PyYAML; extra == "dev"
Dynamic: license-file
